[
 {
   "adm_code": "SY0204",
   "municipality": "A'zaz",
   "sector": "Shelter/Settlement/NFI",
   "activity": "Distribution",
   "organisation": "Japanese Red Cross",
   "status": "Completed",
   "startdate": "2015",
   "enddate": "2015",
   "moreinfo": "Plastic Rolls",
   "quantity": 100
 },
 {
   "adm_code": "SY0200",
   "municipality": "Jebel Saman",
   "sector": "Shelter/Settlement/NFI",
   "activity": "Distribution",
   "organisation": "OFDA",
   "status": "Completed",
   "startdate": "2015",
   "enddate": "2015",
   "moreinfo": "Blankets",
   "quantity": 4897
 },
 {
   "adm_code": "SY0200",
   "municipality": "Jebel Saman",
   "sector": "Food Security/Nutrition/Livelihood",
   "activity": "Distribution",
   "organisation": "China Red Cross",
   "status": "Completed",
   "startdate": "2015",
   "enddate": "2015",
   "moreinfo": "Food parcels",
   "quantity": 325
 },
 {
   "adm_code": "SY0200",
   "municipality": "Jebel Saman",
   "sector": "Food Security/Nutrition/Livelihood",
   "activity": "Distribution",
   "organisation": "Italian Red Cross",
   "status": "Completed",
   "startdate": "2015",
   "enddate": "2015",
   "moreinfo": "Food parcels",
   "quantity": 1016
 },
 {
   "adm_code": "SY0200",
   "municipality": "Jebel Saman",
   "sector": "Food Security/Nutrition/Livelihood",
   "activity": "Distribution",
   "organisation": "Netherlands Red Cross",
   "status": "Completed",
   "startdate": "2015",
   "enddate": "2015",
   "moreinfo": "Food parcels",
   "quantity": 15660
 },
 {
   "adm_code": "SY0200",
   "municipality": "Jebel Saman",
   "sector": "Food Security/Nutrition/Livelihood",
   "activity": "Distribution",
   "organisation": "Taiwan Red Cross",
   "status": "Completed",
   "startdate": "2015",
   "enddate": "2015",
   "moreinfo": "Food parcels",
   "quantity": 2628
 },
 {
   "adm_code": "SY0200",
   "municipality": "Jebel Saman",
   "sector": "WASH/WATSAN",
   "activity": "Distribution",
   "organisation": "Australian Red Cross",
   "status": "Completed",
   "startdate": "2015",
   "enddate": "2015",
   "moreinfo": "Hygiene kits",
   "quantity": 2077
 },
 {
   "adm_code": "SY0200",
   "municipality": "Jebel Saman",
   "sector": "WASH/WATSAN",
   "activity": "Distribution",
   "organisation": "British Red Cross",
   "status": "Completed",
   "startdate": "2015",
   "enddate": "2015",
   "moreinfo": "Hygiene kits",
   "quantity": 15039
 },
 {
   "adm_code": "SY0200",
   "municipality": "Jebel Saman",
   "sector": "WASH/WATSAN",
   "activity": "Distribution",
   "organisation": "Swedish Red Cross",
   "status": "Completed",
   "startdate": "2015",
   "enddate": "2015",
   "moreinfo": "Hygiene kits",
   "quantity": 10564
 },
 {
   "adm_code": "SY0200",
   "municipality": "Jebel Saman",
   "sector": "Shelter/Settlement/NFI",
   "activity": "Distribution",
   "organisation": "Japanese Red Cross",
   "status": "Completed",
   "startdate": "2015",
   "enddate": "2015",
   "moreinfo": "Plastic Rolls",
   "quantity": 2938
 },
 {
   "adm_code": "SY0200",
   "municipality": "Jebel Saman",
   "sector": "Shelter/Settlement/NFI",
   "activity": "Distribution",
   "organisation": "British Red Cross",
   "status": "Completed",
   "startdate": "2015",
   "enddate": "2015",
   "moreinfo": "Sleeping Mat(Moquette) ",
   "quantity": 2705
 },
 {
   "adm_code": "SY0200",
   "municipality": "Jebel Saman",
   "sector": "Shelter/Settlement/NFI",
   "activity": "Distribution",
   "organisation": "OFDA",
   "status": "Completed",
   "startdate": "2015",
   "enddate": "2015",
   "moreinfo": "Sleeping Mat(Moquette) ",
   "quantity": 1388
 },
 {
   "adm_code": "SY0200",
   "municipality": "Jebel Saman",
   "sector": "Protection",
   "activity": "Distribution",
   "organisation": "Swedish Red Cross",
   "status": "Completed",
   "startdate": "2015",
   "enddate": "2015",
   "moreinfo": "Dignity Kits/Women's Emergency kits",
   "quantity": 505
 },
 {
   "adm_code": "SY0100",
   "municipality": "Damascus",
   "sector": "Shelter/Settlement/NFI",
   "activity": "Distribution",
   "organisation": "British Red Cross",
   "status": "Completed",
   "startdate": "2015",
   "enddate": "2015",
   "moreinfo": "Blankets",
   "quantity": 2000
 },
 {
   "adm_code": "SY0100",
   "municipality": "Damascus",
   "sector": "Food Security/Nutrition/Livelihood",
   "activity": "Distribution",
   "organisation": "Netherlands Red Cross",
   "status": "Completed",
   "startdate": "2015",
   "enddate": "2015",
   "moreinfo": "Food parcels",
   "quantity": 12848
 },
 {
   "adm_code": "SY0100",
   "municipality": "Damascus",
   "sector": "Food Security/Nutrition/Livelihood",
   "activity": "Distribution",
   "organisation": "Swedish Red Cross",
   "status": "Completed",
   "startdate": "2015",
   "enddate": "2015",
   "moreinfo": "Food parcels",
   "quantity": 1000
 },
 {
   "adm_code": "SY0100",
   "municipality": "Damascus",
   "sector": "WASH/WATSAN",
   "activity": "Distribution",
   "organisation": "Australian Red Cross",
   "status": "Completed",
   "startdate": "2015",
   "enddate": "2015",
   "moreinfo": "Hygiene kits",
   "quantity": 861
 },
 {
   "adm_code": "SY0100",
   "municipality": "Damascus",
   "sector": "WASH/WATSAN",
   "activity": "Distribution",
   "organisation": "British Red Cross",
   "status": "Completed",
   "startdate": "2015",
   "enddate": "2015",
   "moreinfo": "Hygiene kits",
   "quantity": 2413
 },
 {
   "adm_code": "SY0100",
   "municipality": "Damascus",
   "sector": "WASH/WATSAN",
   "activity": "Distribution",
   "organisation": "OFDA",
   "status": "Completed",
   "startdate": "2015",
   "enddate": "2015",
   "moreinfo": "Hygiene kits",
   "quantity": 2288
 },
 {
   "adm_code": "SY0100",
   "municipality": "Damascus",
   "sector": "WASH/WATSAN",
   "activity": "Distribution",
   "organisation": "Swedish Red Cross",
   "status": "Completed",
   "startdate": "2015",
   "enddate": "2015",
   "moreinfo": "Hygiene kits",
   "quantity": 1862
 },
 {
   "adm_code": "SY0100",
   "municipality": "Damascus",
   "sector": "Shelter/Settlement/NFI",
   "activity": "Distribution",
   "organisation": "ECHO",
   "status": "Completed",
   "startdate": "2015",
   "enddate": "2015",
   "moreinfo": "Kitchen sets",
   "quantity": 6968
 },
 {
   "adm_code": "SY0100",
   "municipality": "Damascus",
   "sector": "Shelter/Settlement/NFI",
   "activity": "Distribution",
   "organisation": "British Red Cross",
   "status": "Completed",
   "startdate": "2015",
   "enddate": "2015",
   "moreinfo": "Mattresses",
   "quantity": 2108
 },
 {
   "adm_code": "SY0100",
   "municipality": "Damascus",
   "sector": "Shelter/Settlement/NFI",
   "activity": "Distribution",
   "organisation": "Japanese Red Cross",
   "status": "Completed",
   "startdate": "2015",
   "enddate": "2015",
   "moreinfo": "Plastic Rolls",
   "quantity": 2973
 },
 {
   "adm_code": "SY0406",
   "municipality": "Al Makhrim",
   "sector": "Food Security/Nutrition/Livelihood",
   "activity": "Distribution",
   "organisation": "Netherlands Red Cross",
   "status": "Completed",
   "startdate": "2015",
   "enddate": "2015",
   "moreinfo": "Food parcels",
   "quantity": 165
 },
 {
   "adm_code": "SY0406",
   "municipality": "Al Makhrim",
   "sector": "Food Security/Nutrition/Livelihood",
   "activity": "Distribution",
   "organisation": "Swedish Red Cross",
   "status": "Completed",
   "startdate": "2015",
   "enddate": "2015",
   "moreinfo": "Food parcels",
   "quantity": 1900
 },
 {
   "adm_code": "SY0406",
   "municipality": "Al Makhrim",
   "sector": "WASH/WATSAN",
   "activity": "Distribution",
   "organisation": "Italian Red Cross",
   "status": "Completed",
   "startdate": "2015",
   "enddate": "2015",
   "moreinfo": "Hygiene kits",
   "quantity": 70
 },
 {
   "adm_code": "SY0406",
   "municipality": "Al Makhrim",
   "sector": "Food Security/Nutrition/Livelihood",
   "activity": "Distribution",
   "organisation": "Swedish Red Cross",
   "status": "Completed",
   "startdate": "2015",
   "enddate": "2015",
   "moreinfo": "Food parcels",
   "quantity": 760
 },
 {
   "adm_code": "SY0402",
   "municipality": "Al Quasir",
   "sector": "Shelter/Settlement/NFI",
   "activity": "Distribution",
   "organisation": "British Red Cross",
   "status": "Completed",
   "startdate": "2015",
   "enddate": "2015",
   "moreinfo": "Blankets",
   "quantity": 8000
 },
 {
   "adm_code": "SY0402",
   "municipality": "Al Quasir",
   "sector": "Food Security/Nutrition/Livelihood",
   "activity": "Distribution",
   "organisation": "Norway Red Cross",
   "status": "Completed",
   "startdate": "2015",
   "enddate": "2015",
   "moreinfo": "Food parcels",
   "quantity": 360
 },
 {
   "adm_code": "SY0402",
   "municipality": "Al Quasir",
   "sector": "WASH/WATSAN",
   "activity": "Distribution",
   "organisation": "British Red Cross",
   "status": "Completed",
   "startdate": "2015",
   "enddate": "2015",
   "moreinfo": "Hygiene kits",
   "quantity": 360
 },
 {
   "adm_code": "SY0402",
   "municipality": "Al Quasir",
   "sector": "WASH/WATSAN",
   "activity": "Distribution",
   "organisation": "Italian Red Cross",
   "status": "Completed",
   "startdate": "2015",
   "enddate": "2015",
   "moreinfo": "Hygiene kits",
   "quantity": 593
 },
 {
   "adm_code": "SY0402",
   "municipality": "Al Quasir",
   "sector": "Shelter/Settlement/NFI",
   "activity": "Distribution",
   "organisation": "Netherlands Red Cross",
   "status": "Completed",
   "startdate": "2015",
   "enddate": "2015",
   "moreinfo": "Mattresses",
   "quantity": 500
 },
 {
   "adm_code": "SY0402",
   "municipality": "Al Quasir",
   "sector": "Shelter/Settlement/NFI",
   "activity": "Distribution",
   "organisation": "Swedish Red Cross",
   "status": "Completed",
   "startdate": "2015",
   "enddate": "2015",
   "moreinfo": "Mattresses",
   "quantity": 1500
 },
 {
   "adm_code": "SY0402",
   "municipality": "Al Quasir",
   "sector": "Shelter/Settlement/NFI",
   "activity": "Distribution",
   "organisation": "British Red Cross",
   "status": "Completed",
   "startdate": "2015",
   "enddate": "2015",
   "moreinfo": "Sleeping Mat(Moquette) ",
   "quantity": 3300
 },
 {
   "adm_code": "SY0402",
   "municipality": "Al Quasir",
   "sector": "Shelter/Settlement/NFI",
   "activity": "Distribution",
   "organisation": "Japanese Red Cross",
   "status": "Completed",
   "startdate": "2015",
   "enddate": "2015",
   "moreinfo": "Sleeping Mat(Moquette) ",
   "quantity": 850
 },
 {
   "adm_code": "SY0404",
   "municipality": "Ar Rastan",
   "sector": "WASH/WATSAN",
   "activity": "Distribution",
   "organisation": "Italian Red Cross",
   "status": "Completed",
   "startdate": "2015",
   "enddate": "2015",
   "moreinfo": "Hygiene kits",
   "quantity": 790
 },
 {
   "adm_code": "SY0401",
   "municipality": "Homs",
   "sector": "Shelter/Settlement/NFI",
   "activity": "Distribution",
   "organisation": "British Red Cross",
   "status": "Completed",
   "startdate": "2015",
   "enddate": "2015",
   "moreinfo": "Blankets",
   "quantity": 8200
 },
 {
   "adm_code": "SY0401",
   "municipality": "Homs",
   "sector": "Food Security/Nutrition/Livelihood",
   "activity": "Distribution",
   "organisation": "Taiwan Red Cross",
   "status": "Completed",
   "startdate": "2015",
   "enddate": "2015",
   "moreinfo": "Food parcels",
   "quantity": 304
 },
 {
   "adm_code": "SY0401",
   "municipality": "Homs",
   "sector": "Shelter/Settlement/NFI",
   "activity": "Distribution",
   "organisation": "Netherlands Red Cross",
   "status": "Completed",
   "startdate": "2015",
   "enddate": "2015",
   "moreinfo": "Mattresses",
   "quantity": 1500
 },
 {
   "adm_code": "SY0401",
   "municipality": "Homs",
   "sector": "Shelter/Settlement/NFI",
   "activity": "Distribution",
   "organisation": "Swedish Red Cross",
   "status": "Completed",
   "startdate": "2015",
   "enddate": "2015",
   "moreinfo": "Mattresses",
   "quantity": 1500
 },
 {
   "adm_code": "SY0401",
   "municipality": "Homs",
   "sector": "Shelter/Settlement/NFI",
   "activity": "Distribution",
   "organisation": "Japanese Red Cross",
   "status": "Completed",
   "startdate": "2015",
   "enddate": "2015",
   "moreinfo": "Plastic Rolls",
   "quantity": 212
 },
 {
   "adm_code": "SY0401",
   "municipality": "Homs",
   "sector": "Shelter/Settlement/NFI",
   "activity": "Distribution",
   "organisation": "British Red Cross",
   "status": "Completed",
   "startdate": "2015",
   "enddate": "2015",
   "moreinfo": "Sleeping Mat(Moquette) ",
   "quantity": 3000
 },
 {
   "adm_code": "SY0401",
   "municipality": "Homs",
   "sector": "Shelter/Settlement/NFI",
   "activity": "Distribution",
   "organisation": "British Red Cross",
   "status": "Completed",
   "startdate": "2015",
   "enddate": "2015",
   "moreinfo": "Blankets",
   "quantity": 4350
 },
 {
   "adm_code": "SY0401",
   "municipality": "Homs",
   "sector": "Food Security/Nutrition/Livelihood",
   "activity": "Distribution",
   "organisation": "Netherlands Red Cross",
   "status": "Completed",
   "startdate": "2015",
   "enddate": "2015",
   "moreinfo": "Food parcels",
   "quantity": 147
 },
 {
   "adm_code": "SY0401",
   "municipality": "Homs",
   "sector": "Food Security/Nutrition/Livelihood",
   "activity": "Distribution",
   "organisation": "Swedish Red Cross",
   "status": "Completed",
   "startdate": "2015",
   "enddate": "2015",
   "moreinfo": "Food parcels",
   "quantity": 476
 },
 {
   "adm_code": "SY0401",
   "municipality": "Homs",
   "sector": "WASH/WATSAN",
   "activity": "Distribution",
   "organisation": "Italian Red Cross",
   "status": "Completed",
   "startdate": "2015",
   "enddate": "2015",
   "moreinfo": "Hygiene kits",
   "quantity": 655
 },
 {
   "adm_code": "SY0401",
   "municipality": "Homs",
   "sector": "Shelter/Settlement/NFI",
   "activity": "Distribution",
   "organisation": "British Red Cross",
   "status": "Completed",
   "startdate": "2015",
   "enddate": "2015",
   "moreinfo": "Mattresses",
   "quantity": 4000
 },
 {
   "adm_code": "SY0401",
   "municipality": "Homs",
   "sector": "Shelter/Settlement/NFI",
   "activity": "Distribution",
   "organisation": "Japanese Red Cross",
   "status": "Completed",
   "startdate": "2015",
   "enddate": "2015",
   "moreinfo": "Plastic Rolls",
   "quantity": 100
 },
 {
   "adm_code": "SY0401",
   "municipality": "Homs",
   "sector": "Shelter/Settlement/NFI",
   "activity": "Distribution",
   "organisation": "British Red Cross",
   "status": "Completed",
   "startdate": "2015",
   "enddate": "2015",
   "moreinfo": "Sleeping Mat(Moquette) ",
   "quantity": 4318
 },
 {
   "adm_code": "SY0401",
   "municipality": "Homs",
   "sector": "Shelter/Settlement/NFI",
   "activity": "Distribution",
   "organisation": "British Red Cross",
   "status": "Completed",
   "startdate": "2015",
   "enddate": "2015",
   "moreinfo": "Blankets",
   "quantity": 41976
 },
 {
   "adm_code": "SY0401",
   "municipality": "Homs",
   "sector": "Food Security/Nutrition/Livelihood",
   "activity": "Distribution",
   "organisation": "Italian Red Cross",
   "status": "Completed",
   "startdate": "2015",
   "enddate": "2015",
   "moreinfo": "Food parcels",
   "quantity": 1542
 },
 {
   "adm_code": "SY0401",
   "municipality": "Homs",
   "sector": "Food Security/Nutrition/Livelihood",
   "activity": "Distribution",
   "organisation": "Netherlands Red Cross",
   "status": "Completed",
   "startdate": "2015",
   "enddate": "2015",
   "moreinfo": "Food parcels",
   "quantity": 10274
 },
 {
   "adm_code": "SY0401",
   "municipality": "Homs",
   "sector": "Food Security/Nutrition/Livelihood",
   "activity": "Distribution",
   "organisation": "Norway Red Cross",
   "status": "Completed",
   "startdate": "2015",
   "enddate": "2015",
   "moreinfo": "Food parcels",
   "quantity": 456
 },
 {
   "adm_code": "SY0401",
   "municipality": "Homs",
   "sector": "WASH/WATSAN",
   "activity": "Distribution",
   "organisation": "Australian Red Cross",
   "status": "Completed",
   "startdate": "2015",
   "enddate": "2015",
   "moreinfo": "Hygiene kits",
   "quantity": 1030
 },
 {
   "adm_code": "SY0401",
   "municipality": "Homs",
   "sector": "WASH/WATSAN",
   "activity": "Distribution",
   "organisation": "British Red Cross",
   "status": "Completed",
   "startdate": "2015",
   "enddate": "2015",
   "moreinfo": "Hygiene kits",
   "quantity": 3337
 },
 {
   "adm_code": "SY0401",
   "municipality": "Homs",
   "sector": "WASH/WATSAN",
   "activity": "Distribution",
   "organisation": "Italian Red Cross",
   "status": "Completed",
   "startdate": "2015",
   "enddate": "2015",
   "moreinfo": "Hygiene kits",
   "quantity": 5297
 },
 {
   "adm_code": "SY0401",
   "municipality": "Homs",
   "sector": "WASH/WATSAN",
   "activity": "Distribution",
   "organisation": "British Red Cross",
   "status": "Completed",
   "startdate": "2015",
   "enddate": "2015",
   "moreinfo": "Hygiene kits",
   "quantity": 181
 },
 {
   "adm_code": "SY0401",
   "municipality": "Homs",
   "sector": "WASH/WATSAN",
   "activity": "Distribution",
   "organisation": "OFDA",
   "status": "Completed",
   "startdate": "2015",
   "enddate": "2015",
   "moreinfo": "Hygiene kits",
   "quantity": 2530
 },
 {
   "adm_code": "SY0401",
   "municipality": "Homs",
   "sector": "WASH/WATSAN",
   "activity": "Distribution",
   "organisation": "Swedish Red Cross",
   "status": "Completed",
   "startdate": "2015",
   "enddate": "2015",
   "moreinfo": "Hygiene kits",
   "quantity": 6269
 },
 {
   "adm_code": "SY0401",
   "municipality": "Homs",
   "sector": "Shelter/Settlement/NFI",
   "activity": "Distribution",
   "organisation": "British Red Cross",
   "status": "Completed",
   "startdate": "2015",
   "enddate": "2015",
   "moreinfo": "Mattresses",
   "quantity": 430
 },
 {
   "adm_code": "SY0401",
   "municipality": "Homs",
   "sector": "Shelter/Settlement/NFI",
   "activity": "Distribution",
   "organisation": "British Red Cross",
   "status": "Completed",
   "startdate": "2015",
   "enddate": "2015",
   "moreinfo": "Sleeping Mat(Moquette) ",
   "quantity": 12983
 },
 {
   "adm_code": "SY0401",
   "municipality": "Homs",
   "sector": "Shelter/Settlement/NFI",
   "activity": "Distribution",
   "organisation": "British Red Cross",
   "status": "Completed",
   "startdate": "2015",
   "enddate": "2015",
   "moreinfo": "Sleeping Mat(Moquette) ",
   "quantity": 5550
 },
 {
   "adm_code": "SY0401",
   "municipality": "Homs",
   "sector": "Food Security/Nutrition/Livelihood",
   "activity": "Distribution",
   "organisation": "Swedish Red Cross",
   "status": "Completed",
   "startdate": "2015",
   "enddate": "2015",
   "moreinfo": "Food parcels",
   "quantity": 353
 },
 {
   "adm_code": "SY0401",
   "municipality": "Homs",
   "sector": "WASH/WATSAN",
   "activity": "Distribution",
   "organisation": "Italian Red Cross",
   "status": "Completed",
   "startdate": "2015",
   "enddate": "2015",
   "moreinfo": "Hygiene kits",
   "quantity": 360
 },
 {
   "adm_code": "SY0401",
   "municipality": "Homs",
   "sector": "Shelter/Settlement/NFI",
   "activity": "Distribution",
   "organisation": "British Red Cross",
   "status": "Completed",
   "startdate": "2015",
   "enddate": "2015",
   "moreinfo": "Sleeping Mat(Moquette) ",
   "quantity": 80
 },
 {
   "adm_code": "SY0401",
   "municipality": "Homs",
   "sector": "Shelter/Settlement/NFI",
   "activity": "Distribution",
   "organisation": "British Red Cross",
   "status": "Completed",
   "startdate": "2015",
   "enddate": "2015",
   "moreinfo": "Sleeping Mat(Moquette) ",
   "quantity": 250
 },
 {
   "adm_code": "SY0401",
   "municipality": "Homs",
   "sector": "WASH/WATSAN",
   "activity": "Distribution",
   "organisation": "OFDA",
   "status": "Completed",
   "startdate": "2015",
   "enddate": "2015",
   "moreinfo": "Hygiene kits",
   "quantity": 1500
 },
 {
   "adm_code": "SY0403",
   "municipality": "Tall Kalakh",
   "sector": "Shelter/Settlement/NFI",
   "activity": "Distribution",
   "organisation": "British Red Cross",
   "status": "Completed",
   "startdate": "2015",
   "enddate": "2015",
   "moreinfo": "Sleeping Mat(Moquette) ",
   "quantity": 1247
 },
 {
   "adm_code": "SY0403",
   "municipality": "Tall Kalakh",
   "sector": "WASH/WATSAN",
   "activity": "Distribution",
   "organisation": "Italian Red Cross",
   "status": "Completed",
   "startdate": "2015",
   "enddate": "2015",
   "moreinfo": "Hygiene kits",
   "quantity": 1205
 },
 {
   "adm_code": "SY0403",
   "municipality": "Tall Kalakh",
   "sector": "Shelter/Settlement/NFI",
   "activity": "Distribution",
   "organisation": "British Red Cross",
   "status": "Completed",
   "startdate": "2015",
   "enddate": "2015",
   "moreinfo": "Blankets",
   "quantity": 2500
 },
 {
   "adm_code": "SY0403",
   "municipality": "Tall Kalakh",
   "sector": "WASH/WATSAN",
   "activity": "Distribution",
   "organisation": "Australian Red Cross",
   "status": "Completed",
   "startdate": "2015",
   "enddate": "2015",
   "moreinfo": "Hygiene kits",
   "quantity": 2442
 },
 {
   "adm_code": "SY0403",
   "municipality": "Tall Kalakh",
   "sector": "WASH/WATSAN",
   "activity": "Distribution",
   "organisation": "Finnish Red Cross",
   "status": "Completed",
   "startdate": "2015",
   "enddate": "2015",
   "moreinfo": "Hygiene kits",
   "quantity": 3408
 },
 {
   "adm_code": "SY0403",
   "municipality": "Tall Kalakh",
   "sector": "WASH/WATSAN",
   "activity": "Distribution",
   "organisation": "OFDA",
   "status": "Completed",
   "startdate": "2015",
   "enddate": "2015",
   "moreinfo": "Hygiene kits",
   "quantity": 1601
 },
 {
   "adm_code": "SY0401",
   "municipality": "Homs",
   "sector": "Food Security/Nutrition/Livelihood",
   "activity": "Distribution",
   "organisation": "Swedish Red Cross",
   "status": "Completed",
   "startdate": "2015",
   "enddate": "2015",
   "moreinfo": "Food parcels",
   "quantity": 1000
 },
 {
   "adm_code": "SY0602",
   "municipality": "Jablah",
   "sector": "WASH/WATSAN",
   "activity": "Distribution",
   "organisation": "British Red Cross",
   "status": "Completed",
   "startdate": "2015",
   "enddate": "2015",
   "moreinfo": "Hygiene kits",
   "quantity": 1300
 },
 {
   "adm_code": "SY0307",
   "municipality": "Az Zabdani",
   "sector": "Food Security/Nutrition/Livelihood",
   "activity": "Distribution",
   "organisation": "Netherlands Red Cross",
   "status": "Completed",
   "startdate": "2015",
   "enddate": "2015",
   "moreinfo": "Food parcels",
   "quantity": 22500
 },
 {
   "adm_code": "SY0302",
   "municipality": "Duma",
   "sector": "Food Security/Nutrition/Livelihood",
   "activity": "Distribution",
   "organisation": "Netherlands Red Cross",
   "status": "Completed",
   "startdate": "2015",
   "enddate": "2015",
   "moreinfo": "Food parcels",
   "quantity": 600
 },
 {
   "adm_code": "SY0302",
   "municipality": "Duma",
   "sector": "WASH/WATSAN",
   "activity": "Distribution",
   "organisation": "Australian Red Cross",
   "status": "Completed",
   "startdate": "2015",
   "enddate": "2015",
   "moreinfo": "Hygiene kits",
   "quantity": 600
 },
 {
   "adm_code": "SY0308",
   "municipality": "Qatana",
   "sector": "Protection",
   "activity": "Distribution",
   "organisation": "Swedish Red Cross",
   "status": "Completed",
   "startdate": "2015",
   "enddate": "2015",
   "moreinfo": "Dignity Kits/Women's Emergency kits",
   "quantity": 108
 },
 {
   "adm_code": "SY0308",
   "municipality": "Qatana",
   "sector": "Food Security/Nutrition/Livelihood",
   "activity": "Distribution",
   "organisation": "Netherlands Red Cross",
   "status": "Completed",
   "startdate": "2015",
   "enddate": "2015",
   "moreinfo": "Food parcels",
   "quantity": 6000
 },
 {
   "adm_code": "SY0308",
   "municipality": "Qatana",
   "sector": "Shelter/Settlement/NFI",
   "activity": "Distribution",
   "organisation": "ECHO",
   "status": "Completed",
   "startdate": "2015",
   "enddate": "2015",
   "moreinfo": "Kitchen sets",
   "quantity": 450
 },
 {
   "adm_code": "SY0308",
   "municipality": "Qatana",
   "sector": "Protection",
   "activity": "Distribution",
   "organisation": "Swedish Red Cross",
   "status": "Completed",
   "startdate": "2015",
   "enddate": "2015",
   "moreinfo": "Dignity Kits/Women's Emergency kits",
   "quantity": 1053
 },
 {
   "adm_code": "SY0308",
   "municipality": "Qatana",
   "sector": "Protection",
   "activity": "Distribution",
   "organisation": "Swedish Red Cross",
   "status": "Completed",
   "startdate": "2015",
   "enddate": "2015",
   "moreinfo": "Dignity Kits/Women's Emergency kits",
   "quantity": 97
 },
 {
   "adm_code": "SY0301",
   "municipality": "Rural Damascus",
   "sector": "Food Security/Nutrition/Livelihood",
   "activity": "Distribution",
   "organisation": "British Red Cross",
   "status": "Completed",
   "startdate": "2015",
   "enddate": "2015",
   "moreinfo": "Food parcels",
   "quantity": 3000
 },
 {
   "adm_code": "SY0301",
   "municipality": "Rural Damascus",
   "sector": "Food Security/Nutrition/Livelihood",
   "activity": "Distribution",
   "organisation": "Netherlands Red Cross",
   "status": "Completed",
   "startdate": "2015",
   "enddate": "2015",
   "moreinfo": "Food parcels",
   "quantity": 19400
 },
 {
   "adm_code": "SY0301",
   "municipality": "Rural Damascus",
   "sector": "WASH/WATSAN",
   "activity": "Distribution",
   "organisation": "Swedish Red Cross",
   "status": "Completed",
   "startdate": "2015",
   "enddate": "2015",
   "moreinfo": "Hygiene kits",
   "quantity": 300
 },
 {
   "adm_code": "SY0301",
   "municipality": "Rural Damascus",
   "sector": "Food Security/Nutrition/Livelihood",
   "activity": "Distribution",
   "organisation": "Netherlands Red Cross",
   "status": "Completed",
   "startdate": "2015",
   "enddate": "2015",
   "moreinfo": "Food parcels",
   "quantity": 4000
 },
 {
   "adm_code": "SY0301",
   "municipality": "Rural Damascus",
   "sector": "Shelter/Settlement/NFI",
   "activity": "Distribution",
   "organisation": "ECHO",
   "status": "Completed",
   "startdate": "2015",
   "enddate": "2015",
   "moreinfo": "Kitchen sets",
   "quantity": 500
 },
 {
   "adm_code": "SY0301",
   "municipality": "Rural Damascus",
   "sector": "Health",
   "activity": "Mobile health unit",
   "organisation": "Swedish Red Cross",
   "status": "Completed",
   "startdate": "2015",
   "enddate": "2015",
   "moreinfo": "Mobile Health Units (specify in comments)",
   "quantity": 3
 },
 {
   "adm_code": "SY0100",
   "municipality": "Damascus",
   "sector": "Health",
   "activity": "Mobile health unit",
   "organisation": "Swedish Red Cross",
   "status": "Completed",
   "startdate": "2015",
   "enddate": "2015",
   "moreinfo": "Mobile Health Units (specify in comments)",
   "quantity": 1
 },
 {
   "adm_code": "SY0401",
   "municipality": "Homs",
   "sector": "Health",
   "activity": "Mobile health unit",
   "organisation": "Swedish Red Cross",
   "status": "Completed",
   "startdate": "2015",
   "enddate": "2015",
   "moreinfo": "Mobile Health Units (specify in comments)",
   "quantity": 1
 },
 {
   "adm_code": "SY0902",
   "municipality": "Abu Kamal",
   "sector": "Health",
   "activity": "Mobile health unit",
   "organisation": "Swedish Red Cross",
   "status": "Completed",
   "startdate": "2015",
   "enddate": "2015",
   "moreinfo": "Mobile Health Units (specify in comments)",
   "quantity": 1
 },
 {
   "adm_code": "SY1400",
   "municipality": "Quneitra",
   "sector": "Health",
   "activity": "Mobile health unit",
   "organisation": "Swedish Red Cross",
   "status": "Completed",
   "startdate": "2015",
   "enddate": "2015",
   "moreinfo": "Mobile Health Units (specify in comments)",
   "quantity": 1
 },
 {
   "adm_code": "SY1000",
   "municipality": "Tartous",
   "sector": "Health",
   "activity": "Mobile health unit",
   "organisation": "Swedish Red Cross",
   "status": "Completed",
   "startdate": "2015",
   "enddate": "2015",
   "moreinfo": "Mobile Health Units (specify in comments)",
   "quantity": 1
 },
 {
   "adm_code": "SY0802",
   "municipality": "Quamishli",
   "sector": "Health",
   "activity": "Primary health clinics",
   "organisation": "Swedish Red Cross",
   "status": "Completed",
   "startdate": "2015",
   "enddate": "2015",
   "moreinfo": "Primary Health/Clinics",
   "quantity": 1
 },
 {
   "adm_code": "SY0800",
   "municipality": "Al-Hasakeh",
   "sector": "Health",
   "activity": "Primary health clinics",
   "organisation": "Swedish Red Cross",
   "status": "Completed",
   "startdate": "2015",
   "enddate": "2015",
   "moreinfo": "Primary Health/Clinics",
   "quantity": 1
 },
 {
   "adm_code": "SY0304",
   "municipality": "At Tall",
   "sector": "Health",
   "activity": "Primary health clinics",
   "organisation": "Swedish Red Cross",
   "status": "Completed",
   "startdate": "2015",
   "enddate": "2015",
   "moreinfo": "Primary Health/Clinics",
   "quantity": 1
 },
 {
   "adm_code": "SY0301",
   "municipality": "Rural Damascus",
   "sector": "Health",
   "activity": "Primary health clinics",
   "organisation": "Swedish Red Cross",
   "status": "Completed",
   "startdate": "2015",
   "enddate": "2015",
   "moreinfo": "Primary Health/Clinics",
   "quantity": 1
 },
 {
   "adm_code": "SY0100",
   "municipality": "Damascus",
   "sector": "Health",
   "activity": "Primary health clinics",
   "organisation": "Swedish Red Cross",
   "status": "Completed",
   "startdate": "2015",
   "enddate": "2015",
   "moreinfo": "Primary Health/Clinics",
   "quantity": 1
 },
 {
   "adm_code": "SY0100",
   "municipality": "Damascus",
   "sector": "Health",
   "activity": "Primary health clinics",
   "organisation": "Swedish Red Cross",
   "status": "Completed",
   "startdate": "2015",
   "enddate": "2015",
   "moreinfo": "Primary Health/Clinics",
   "quantity": 1
 },
 {
   "adm_code": "SY0401",
   "municipality": "Homs",
   "sector": "Health",
   "activity": "Primary health clinics",
   "organisation": "Swedish Red Cross",
   "status": "Completed",
   "startdate": "2015",
   "enddate": "2015",
   "moreinfo": "Primary Health/Clinics",
   "quantity": 1
 },
 {
   "adm_code": "SY0405",
   "municipality": "Tadmor",
   "sector": "Health",
   "activity": "Primary health clinics",
   "organisation": "Swedish Red Cross",
   "status": "Completed",
   "startdate": "2015",
   "enddate": "2015",
   "moreinfo": "Primary Health/Clinics",
   "quantity": 1
 },
 {
   "adm_code": "SY0901",
   "municipality": "Deir-ez-Zor",
   "sector": "Health",
   "activity": "Primary health clinics",
   "organisation": "Swedish Red Cross",
   "status": "Completed",
   "startdate": "2015",
   "enddate": "2015",
   "moreinfo": "Primary Health/Clinics",
   "quantity": 1
 },
 {
   "adm_code": "SY0902",
   "municipality": "Abu Kamal",
   "sector": "Health",
   "activity": "Primary health clinics",
   "organisation": "Swedish Red Cross",
   "status": "Completed",
   "startdate": "2015",
   "enddate": "2015",
   "moreinfo": "Primary Health/Clinics",
   "quantity": 1
 },
 {
   "adm_code": "SY0404",
   "municipality": "Ar Rastan",
   "sector": "Health",
   "activity": "Primary health clinics",
   "organisation": "Swedish Red Cross",
   "status": "Completed",
   "startdate": "2015",
   "enddate": "2015",
   "moreinfo": "Primary Health/Clinics",
   "quantity": 1
 },
 {
   "adm_code": "SY0404",
   "municipality": "Ar Rastan",
   "sector": "Health",
   "activity": "Primary health clinics",
   "organisation": "Swedish Red Cross",
   "status": "Completed",
   "startdate": "2015",
   "enddate": "2015",
   "moreinfo": "Primary Health/Clinics",
   "quantity": 1
 },
 {
   "adm_code": "SY0902",
   "municipality": "Abu Kamal",
   "sector": "Health",
   "activity": "Primary health clinics",
   "organisation": "ECHO",
   "status": "Completed",
   "startdate": "2015",
   "enddate": "2015",
   "moreinfo": "Primary Health/Health Points",
   "quantity": 1
 },
 {
   "adm_code": "SY0302",
   "municipality": "Duma",
   "sector": "Health",
   "activity": "Primary health clinics",
   "organisation": "ECHO",
   "status": "Completed",
   "startdate": "2015",
   "enddate": "2015",
   "moreinfo": "Primary Health/Health Points",
   "quantity": 1
 },
 {
   "adm_code": "SY0302",
   "municipality": "Duma",
   "sector": "Health",
   "activity": "Primary health clinics",
   "organisation": "ECHO",
   "status": "Completed",
   "startdate": "2015",
   "enddate": "2015",
   "moreinfo": "Primary Health/Health Points",
   "quantity": 1
 },
 {
   "adm_code": "SY0301",
   "municipality": "Rural Damascus",
   "sector": "Health",
   "activity": "Primary health clinics",
   "organisation": "ECHO",
   "status": "Completed",
   "startdate": "2015",
   "enddate": "2015",
   "moreinfo": "Primary Health/Health Points",
   "quantity": 1
 },
 {
   "adm_code": "SY0200",
   "municipality": "Jebel Saman",
   "sector": "Shelter/Settlement/NFI",
   "activity": "Distribution",
   "organisation": "British Red Cross",
   "status": "Completed",
   "startdate": "2015",
   "enddate": "2015",
   "moreinfo": "Blankets",
   "quantity": 3478
 },
 {
   "adm_code": "SY0200",
   "municipality": "Jebel Saman",
   "sector": "Food Security/Nutrition/Livelihood",
   "activity": "Distribution",
   "organisation": "Netherlands Red Cross",
   "status": "Completed",
   "startdate": "2015",
   "enddate": "2015",
   "moreinfo": "Food parcels",
   "quantity": 5000
 },
 {
   "adm_code": "SY0200",
   "municipality": "Jebel Saman",
   "sector": "Food Security/Nutrition/Livelihood",
   "activity": "Distribution",
   "organisation": "Swedish Red Cross",
   "status": "Completed",
   "startdate": "2015",
   "enddate": "2015",
   "moreinfo": "Food parcels",
   "quantity": 807
 },
 {
   "adm_code": "SY0200",
   "municipality": "Jebel Saman",
   "sector": "Food Security/Nutrition/Livelihood",
   "activity": "Distribution",
   "organisation": "Taiwan Red Cross",
   "status": "Completed",
   "startdate": "2015",
   "enddate": "2015",
   "moreinfo": "Food parcels",
   "quantity": 1183
 },
 {
   "adm_code": "SY0200",
   "municipality": "Jebel Saman",
   "sector": "WASH/WATSAN",
   "activity": "Distribution",
   "organisation": "OFDA",
   "status": "Completed",
   "startdate": "2015",
   "enddate": "2015",
   "moreinfo": "Hygiene kits",
   "quantity": 3608
 },
 {
   "adm_code": "SY0200",
   "municipality": "Jebel Saman",
   "sector": "WASH/WATSAN",
   "activity": "Distribution",
   "organisation": "Swedish Red Cross",
   "status": "Completed",
   "startdate": "2015",
   "enddate": "2015",
   "moreinfo": "Hygiene kits",
   "quantity": 23
 },
 {
   "adm_code": "SY0200",
   "municipality": "Jebel Saman",
   "sector": "Shelter/Settlement/NFI",
   "activity": "Distribution",
   "organisation": "Japanese Red Cross",
   "status": "Completed",
   "startdate": "2015",
   "enddate": "2015",
   "moreinfo": "Sleeping Mat(Plastic)",
   "quantity": 1920
 },
 {
   "adm_code": "SY0200",
   "municipality": "Jebel Saman",
   "sector": "Shelter/Settlement/NFI",
   "activity": "Distribution",
   "organisation": "British Red Cross",
   "status": "Completed",
   "startdate": "2015",
   "enddate": "2015",
   "moreinfo": "Sleeping Mat(Moquette) ",
   "quantity": 825
 },
 {
   "adm_code": "SY0200",
   "municipality": "Jebel Saman",
   "sector": "Shelter/Settlement/NFI",
   "activity": "Distribution",
   "organisation": "British Red Cross",
   "status": "Completed",
   "startdate": "2015",
   "enddate": "2015",
   "moreinfo": "Sleeping Mat(Moquette) ",
   "quantity": 825
 },
 {
   "adm_code": "SY0100",
   "municipality": "Damascus",
   "sector": "Food Security/Nutrition/Livelihood",
   "activity": "Distribution",
   "organisation": "Netherlands Red Cross",
   "status": "Completed",
   "startdate": "2015",
   "enddate": "2015",
   "moreinfo": "Food parcels",
   "quantity": 3662
 },
 {
   "adm_code": "SY0100",
   "municipality": "Damascus",
   "sector": "WASH/WATSAN",
   "activity": "Distribution",
   "organisation": "OFDA",
   "status": "Completed",
   "startdate": "2015",
   "enddate": "2015",
   "moreinfo": "Hygiene kits",
   "quantity": 2616
 },
 {
   "adm_code": "SY0100",
   "municipality": "Damascus",
   "sector": "Shelter/Settlement/NFI",
   "activity": "Distribution",
   "organisation": "British Red Cross",
   "status": "Completed",
   "startdate": "2015",
   "enddate": "2015",
   "moreinfo": "Mattresses",
   "quantity": 772
 },
 {
   "adm_code": "SY0100",
   "municipality": "Damascus",
   "sector": "Shelter/Settlement/NFI",
   "activity": "Distribution",
   "organisation": "British Red Cross",
   "status": "Completed",
   "startdate": "2015",
   "enddate": "2015",
   "moreinfo": "Sleeping Mat(Moquette) ",
   "quantity": 1332
 },
 {
   "adm_code": "SY0100",
   "municipality": "Damascus",
   "sector": "Shelter/Settlement/NFI",
   "activity": "Distribution",
   "organisation": "Japanese Red Cross",
   "status": "Completed",
   "startdate": "2015",
   "enddate": "2015",
   "moreinfo": "Sleeping Mat(Moquette) ",
   "quantity": 27
 },
 {
   "adm_code": "SY0406",
   "municipality": "Al Makhrim",
   "sector": "Shelter/Settlement/NFI",
   "activity": "Distribution",
   "organisation": "British Red Cross",
   "status": "Completed",
   "startdate": "2015",
   "enddate": "2015",
   "moreinfo": "Blankets",
   "quantity": 5000
 },
 {
   "adm_code": "SY0406",
   "municipality": "Al Makhrim",
   "sector": "Shelter/Settlement/NFI",
   "activity": "Distribution",
   "organisation": "British Red Cross",
   "status": "Completed",
   "startdate": "2015",
   "enddate": "2015",
   "moreinfo": "Mattresses",
   "quantity": 1000
 },
 {
   "adm_code": "SY0406",
   "municipality": "Al Makhrim",
   "sector": "Shelter/Settlement/NFI",
   "activity": "Distribution",
   "organisation": "British Red Cross",
   "status": "Completed",
   "startdate": "2015",
   "enddate": "2015",
   "moreinfo": "Sleeping Mat(Moquette) ",
   "quantity": 3000
 },
 {
   "adm_code": "SY0402",
   "municipality": "Al Quasir",
   "sector": "Shelter/Settlement/NFI",
   "activity": "Distribution",
   "organisation": "British Red Cross",
   "status": "Completed",
   "startdate": "2015",
   "enddate": "2015",
   "moreinfo": "Mattresses",
   "quantity": 190
 },
 {
   "adm_code": "SY0401",
   "municipality": "Homs",
   "sector": "Shelter/Settlement/NFI",
   "activity": "Distribution",
   "organisation": "British Red Cross",
   "status": "Completed",
   "startdate": "2015",
   "enddate": "2015",
   "moreinfo": "Blankets",
   "quantity": 3000
 },
 {
   "adm_code": "SY0401",
   "municipality": "Homs",
   "sector": "Shelter/Settlement/NFI",
   "activity": "Distribution",
   "organisation": "Netherlands Red Cross",
   "status": "Completed",
   "startdate": "2015",
   "enddate": "2015",
   "moreinfo": "Mattresses",
   "quantity": 225
 },
 {
   "adm_code": "SY0401",
   "municipality": "Homs",
   "sector": "Shelter/Settlement/NFI",
   "activity": "Distribution",
   "organisation": "Swedish Red Cross",
   "status": "Completed",
   "startdate": "2015",
   "enddate": "2015",
   "moreinfo": "Mattresses",
   "quantity": 533
 },
 {
   "adm_code": "SY0401",
   "municipality": "Homs",
   "sector": "Shelter/Settlement/NFI",
   "activity": "Distribution",
   "organisation": "British Red Cross",
   "status": "Completed",
   "startdate": "2015",
   "enddate": "2015",
   "moreinfo": "Sleeping Mat(Moquette) ",
   "quantity": 3000
 },
 {
   "adm_code": "SY0401",
   "municipality": "Homs",
   "sector": "Shelter/Settlement/NFI",
   "activity": "Distribution",
   "organisation": "British Red Cross",
   "status": "Completed",
   "startdate": "2015",
   "enddate": "2015",
   "moreinfo": "Blankets",
   "quantity": 9067
 },
 {
   "adm_code": "SY0401",
   "municipality": "Homs",
   "sector": "Food Security/Nutrition/Livelihood",
   "activity": "Distribution",
   "organisation": "Netherlands Red Cross",
   "status": "Completed",
   "startdate": "2015",
   "enddate": "2015",
   "moreinfo": "Food parcels",
   "quantity": 2620
 },
 {
   "adm_code": "SY0401",
   "municipality": "Homs",
   "sector": "WASH/WATSAN",
   "activity": "Distribution",
   "organisation": "OFDA",
   "status": "Completed",
   "startdate": "2015",
   "enddate": "2015",
   "moreinfo": "Hygiene kits",
   "quantity": 11172
 },
 {
   "adm_code": "SY0401",
   "municipality": "Homs",
   "sector": "Shelter/Settlement/NFI",
   "activity": "Distribution",
   "organisation": "British Red Cross",
   "status": "Completed",
   "startdate": "2015",
   "enddate": "2015",
   "moreinfo": "Mattresses",
   "quantity": 11780
 },
 {
   "adm_code": "SY0401",
   "municipality": "Homs",
   "sector": "Shelter/Settlement/NFI",
   "activity": "Distribution",
   "organisation": "Japanese Red Cross",
   "status": "Completed",
   "startdate": "2015",
   "enddate": "2015",
   "moreinfo": "Sleeping Mat(Moquette) ",
   "quantity": 448
 },
 {
   "adm_code": "SY0401",
   "municipality": "Homs",
   "sector": "Shelter/Settlement/NFI",
   "activity": "Distribution",
   "organisation": "British Red Cross",
   "status": "Completed",
   "startdate": "2015",
   "enddate": "2015",
   "moreinfo": "Sleeping Mat(Moquette) ",
   "quantity": 2900
 },
 {
   "adm_code": "SY0401",
   "municipality": "Homs",
   "sector": "Shelter/Settlement/NFI",
   "activity": "Distribution",
   "organisation": "British Red Cross",
   "status": "Completed",
   "startdate": "2015",
   "enddate": "2015",
   "moreinfo": "Sleeping Mat(Moquette) ",
   "quantity": 4000
 },
 {
   "adm_code": "SY0401",
   "municipality": "Homs",
   "sector": "Shelter/Settlement/NFI",
   "activity": "Distribution",
   "organisation": "British Red Cross",
   "status": "Completed",
   "startdate": "2015",
   "enddate": "2015",
   "moreinfo": "Blankets",
   "quantity": 1000
 },
 {
   "adm_code": "SY0401",
   "municipality": "Homs",
   "sector": "Shelter/Settlement/NFI",
   "activity": "Distribution",
   "organisation": "Japanese Red Cross",
   "status": "Completed",
   "startdate": "2015",
   "enddate": "2015",
   "moreinfo": "Sleeping Mat(Moquette) ",
   "quantity": 500
 },
 {
   "adm_code": "SY0401",
   "municipality": "Homs",
   "sector": "Shelter/Settlement/NFI",
   "activity": "Distribution",
   "organisation": "British Red Cross",
   "status": "Completed",
   "startdate": "2015",
   "enddate": "2015",
   "moreinfo": "Blankets",
   "quantity": 1433
 },
 {
   "adm_code": "SY0401",
   "municipality": "Homs",
   "sector": "Food Security/Nutrition/Livelihood",
   "activity": "Distribution",
   "organisation": "Netherlands Red Cross",
   "status": "Completed",
   "startdate": "2015",
   "enddate": "2015",
   "moreinfo": "Food parcels",
   "quantity": 364
 },
 {
   "adm_code": "SY0401",
   "municipality": "Homs",
   "sector": "Shelter/Settlement/NFI",
   "activity": "Distribution",
   "organisation": "British Red Cross",
   "status": "Completed",
   "startdate": "2015",
   "enddate": "2015",
   "moreinfo": "Blankets",
   "quantity": 6000
 },
 {
   "adm_code": "SY0401",
   "municipality": "Homs",
   "sector": "Shelter/Settlement/NFI",
   "activity": "Distribution",
   "organisation": "British Red Cross",
   "status": "Completed",
   "startdate": "2015",
   "enddate": "2015",
   "moreinfo": "Mattresses",
   "quantity": 6000
 },
 {
   "adm_code": "SY0401",
   "municipality": "Homs",
   "sector": "Shelter/Settlement/NFI",
   "activity": "Distribution",
   "organisation": "British Red Cross",
   "status": "Completed",
   "startdate": "2015",
   "enddate": "2015",
   "moreinfo": "Sleeping Mat(Moquette) ",
   "quantity": 3000
 },
 {
   "adm_code": "SY0401",
   "municipality": "Homs",
   "sector": "Shelter/Settlement/NFI",
   "activity": "Distribution",
   "organisation": "British Red Cross",
   "status": "Completed",
   "startdate": "2015",
   "enddate": "2015",
   "moreinfo": "Sleeping Mat(Plastic)",
   "quantity": 6000
 },
 {
   "adm_code": "SY0403",
   "municipality": "Tall Kalakh",
   "sector": "Shelter/Settlement/NFI",
   "activity": "Distribution",
   "organisation": "Japanese Red Cross",
   "status": "Completed",
   "startdate": "2015",
   "enddate": "2015",
   "moreinfo": "Sleeping Mat(Moquette) ",
   "quantity": 1500
 },
 {
   "adm_code": "SY0403",
   "municipality": "Tall Kalakh",
   "sector": "Shelter/Settlement/NFI",
   "activity": "Distribution",
   "organisation": "British Red Cross",
   "status": "Completed",
   "startdate": "2015",
   "enddate": "2015",
   "moreinfo": "Blankets",
   "quantity": 12
 },
 {
   "adm_code": "SY0306",
   "municipality": "An Nabk",
   "sector": "Shelter/Settlement/NFI",
   "activity": "Distribution",
   "organisation": "British Red Cross",
   "status": "Completed",
   "startdate": "2015",
   "enddate": "2015",
   "moreinfo": "Sleeping Mat(Moquette) ",
   "quantity": 1681
 },
 {
   "adm_code": "SY0308",
   "municipality": "Qatana",
   "sector": "WASH/WATSAN",
   "activity": "Distribution",
   "organisation": "OFDA",
   "status": "Completed",
   "startdate": "2015",
   "enddate": "2015",
   "moreinfo": "Hygiene kits",
   "quantity": 50
 },
 {
   "adm_code": "SY0308",
   "municipality": "Qatana",
   "sector": "Shelter/Settlement/NFI",
   "activity": "Distribution",
   "organisation": "British Red Cross",
   "status": "Completed",
   "startdate": "2015",
   "enddate": "2015",
   "moreinfo": "Sleeping Mat(Moquette) ",
   "quantity": 3840
 },
 {
   "adm_code": "SY0301",
   "municipality": "Rural Damascus",
   "sector": "Food Security/Nutrition/Livelihood",
   "activity": "Distribution",
   "organisation": "British Red Cross",
   "status": "Completed",
   "startdate": "2015",
   "enddate": "2015",
   "moreinfo": "Food parcels",
   "quantity": 3000
 },
 {
   "adm_code": "SY0301",
   "municipality": "Rural Damascus",
   "sector": "Food Security/Nutrition/Livelihood",
   "activity": "Distribution",
   "organisation": "Netherlands Red Cross",
   "status": "Completed",
   "startdate": "2015",
   "enddate": "2015",
   "moreinfo": "Food parcels",
   "quantity": 2000
 },
 {
   "adm_code": "SY0301",
   "municipality": "Rural Damascus",
   "sector": "WASH/WATSAN",
   "activity": "Distribution",
   "organisation": "OFDA",
   "status": "Completed",
   "startdate": "2015",
   "enddate": "2015",
   "moreinfo": "Hygiene kits",
   "quantity": 100
 },
 {
   "adm_code": "SY0305",
   "municipality": "Yabrud",
   "sector": "Shelter/Settlement/NFI",
   "activity": "Distribution",
   "organisation": "British Red Cross",
   "status": "Completed",
   "startdate": "2015",
   "enddate": "2015",
   "moreinfo": "Blankets",
   "quantity": 3018
 },
 {
   "adm_code": "SY0305",
   "municipality": "Yabrud",
   "sector": "Shelter/Settlement/NFI",
   "activity": "Distribution",
   "organisation": "British Red Cross",
   "status": "Completed",
   "startdate": "2015",
   "enddate": "2015",
   "moreinfo": "Sleeping Mat(Moquette) ",
   "quantity": 765
 },
 {
   "adm_code": "",
   "municipality": "",
   "sector": "Food Security/Nutrition/Livelihood",
   "activity": "contribution to ICRC Syria country appeal, EUR 150.000",
   "organisation": "Austrian Red Cross",
   "status": "Ongoing",
   "startdate": "01/01/2016",
   "enddate": "31/12/2016",
   "moreinfo": "",
   "quantity": null
 },
 {
   "adm_code": "",
   "municipality": "",
   "sector": "Food Security/Nutrition/Livelihood",
   "activity": "Food parcels",
   "organisation": "British Red Cross",
   "status": "Ongoing",
   "startdate": "01/04/2016",
   "enddate": "30/06/2016",
   "moreinfo": "",
   "quantity": null
 },
 {
   "adm_code": "",
   "municipality": "",
   "sector": "Shelter/Settlement/NFI",
   "activity": "Winterisation NFIs",
   "organisation": "British Red Cross",
   "status": "Ongoing",
   "startdate": "01/11/2015",
   "enddate": "31/03/2016",
   "moreinfo": "",
   "quantity": null
 },
 {
   "adm_code": "",
   "municipality": "",
   "sector": "Shelter/Settlement/NFI",
   "activity": "Winterisation NFIs",
   "organisation": "British Red Cross",
   "status": "Ongoing",
   "startdate": "01/11/2016",
   "enddate": "31/03/2017",
   "moreinfo": "",
   "quantity": null
 },
 {
   "adm_code": "",
   "municipality": "",
   "sector": "Organisational Development",
   "activity": "Broad support (training in DM, health, IM, logistics; establishment of AtB; financial support to branches; volunteer support)",
   "organisation": "British Red Cross",
   "status": "Ongoing",
   "startdate": "01/06/2015",
   "enddate": "30/09/2016",
   "moreinfo": "",
   "quantity": null
 },
 {
   "adm_code": "",
   "municipality": "",
   "sector": "Food Security/Nutrition/Livelihood",
   "activity": "Livelihoods establishment (pilot projects)",
   "organisation": "British Red Cross",
   "status": "Ongoing",
   "startdate": "01/05/2016",
   "enddate": "30/01/2017",
   "moreinfo": "",
   "quantity": null
 },
 {
   "adm_code": "",
   "municipality": "",
   "sector": "Health",
   "activity": "Funding of 5 nutrition centres (staff, mobile teams and CMAM trainings) ",
   "organisation": "Canadian Red Cross",
   "status": "Ongoing",
   "startdate": "01/04/2015",
   "enddate": "31/12/2016",
   "moreinfo": "",
   "quantity": null
 },
 {
   "adm_code": "",
   "municipality": "",
   "sector": "Organisational Development",
   "activity": "Medical logistics support to SARC (implementation of recommendations from medlog assessment) ",
   "organisation": "Canadian Red Cross",
   "status": "Ongoing",
   "startdate": "01/04/2015",
   "enddate": "31/12/2016",
   "moreinfo": "",
   "quantity": null
 },
 {
   "adm_code": "",
   "municipality": "",
   "sector": "Logistics",
   "activity": "Funding of Medical Logistic officer position in Syria (6 months) ",
   "organisation": "Canadian Red Cross",
   "status": "Ongoing",
   "startdate": "14/02/2016",
   "enddate": "13/08/2016",
   "moreinfo": "",
   "quantity": null
 },
 {
   "adm_code": "",
   "municipality": "",
   "sector": "Health",
   "activity": "Provision of nutrition supplements ",
   "organisation": "Canadian Red Cross",
   "status": "Ongoing",
   "startdate": "01/04/2016",
   "enddate": "31/12/2016",
   "moreinfo": "",
   "quantity": null
 },
 {
   "adm_code": "",
   "municipality": "",
   "sector": "Health",
   "activity": "Provision of financial support to OBGYN treatment costs at Homs Hospital",
   "organisation": "Canadian Red Cross",
   "status": "Ongoing",
   "startdate": "01/04/2016",
   "enddate": "31/12/2016",
   "moreinfo": "",
   "quantity": null
 },
 {
   "adm_code": "",
   "municipality": "",
   "sector": "Health",
   "activity": "Provision of Medical Equipement",
   "organisation": "Canadian Red Cross",
   "status": "Ongoing",
   "startdate": "01/04/2016",
   "enddate": "31/12/2016",
   "moreinfo": "",
   "quantity": null
 },
 {
   "adm_code": "",
   "municipality": "",
   "sector": "Health",
   "activity": "Provision of medicines and medical supplies ",
   "organisation": "Canadian Red Cross",
   "status": "Ongoing",
   "startdate": "01/04/2016",
   "enddate": "31/12/2016",
   "moreinfo": "",
   "quantity": null
 },
 {
   "adm_code": "",
   "municipality": "",
   "sector": "Health",
   "activity": "Implementation of CBHFA and other health related trainings",
   "organisation": "Canadian Red Cross",
   "status": "Ongoing",
   "startdate": "01/04/2016",
   "enddate": "31/12/2016",
   "moreinfo": "",
   "quantity": null
 },
 {
   "adm_code": "",
   "municipality": "",
   "sector": "Organisational Development",
   "activity": "Funding of SARC  positions ",
   "organisation": "Canadian Red Cross",
   "status": "Ongoing",
   "startdate": "01/04/2016",
   "enddate": "31/12/2016",
   "moreinfo": "",
   "quantity": null
 },
 {
   "adm_code": "",
   "municipality": "",
   "sector": "Health",
   "activity": "Provision of financial support to ICRC health related activities ",
   "organisation": "Canadian Red Cross",
   "status": "Ongoing",
   "startdate": "01/04/2016",
   "enddate": "31/12/2016",
   "moreinfo": "",
   "quantity": null
 },
 {
   "adm_code": "",
   "municipality": "",
   "sector": "Health",
   "activity": "Provision of emergency mental, primary health care and ambulance services for conflict affected people through 10 Emergency Health Points ",
   "organisation": "Danish Red Cross",
   "status": "Completed",
   "startdate": "01/04/2015",
   "enddate": "30/04/2016",
   "moreinfo": "",
   "quantity": null
 },
 {
   "adm_code": "",
   "municipality": "",
   "sector": "Shelter/Settlement/NFI",
   "activity": "Provision of winterisation relief items (blanket, mattresses and mats )for IDPs and baby kits for children from 0-18 month",
   "organisation": "Danish Red Cross",
   "status": "Completed",
   "startdate": "01/04/2015",
   "enddate": "30/04/2016",
   "moreinfo": "",
   "quantity": null
 },
 {
   "adm_code": "",
   "municipality": "",
   "sector": "Health",
   "activity": "Psychosocial Support in Community Centres and PS Mobile Teams",
   "organisation": "Danish Red Cross",
   "status": "Ongoing",
   "startdate": "01/01/2015",
   "enddate": "31/12/2017",
   "moreinfo": "",
   "quantity": null
 },
 {
   "adm_code": "",
   "municipality": "",
   "sector": "Health",
   "activity": "Psychosocial Support in Community Centres and PS Mobile Teams and PS support for SARC volunteers",
   "organisation": "Danish Red Cross",
   "status": "Ongoing",
   "startdate": "01/11/2014",
   "enddate": "31/08/2016",
   "moreinfo": "",
   "quantity": null
 },
 {
   "adm_code": "",
   "municipality": "",
   "sector": "Organisational Development",
   "activity": "Support for SARC HQ, running of 2 branches and 6 sub-\nbranches",
   "organisation": "Danish Red Cross",
   "status": "Ongoing",
   "startdate": "01/10/2015",
   "enddate": "30/09/2016",
   "moreinfo": "",
   "quantity": null
 },
 {
   "adm_code": "",
   "municipality": "",
   "sector": "Health",
   "activity": "Running of 3 clinics in Shanaya, Jeirud, Latakia",
   "organisation": "Danish Red Cross",
   "status": "Ongoing",
   "startdate": "01/10/2015",
   "enddate": "30/09/2016",
   "moreinfo": "",
   "quantity": null
 },
 {
   "adm_code": "",
   "municipality": "",
   "sector": "WASH/WATSAN",
   "activity": "Provision of 24.000 Family Hygiene Kits",
   "organisation": "Danish Red Cross",
   "status": "Ongoing",
   "startdate": "01/10/2015",
   "enddate": "30/09/2016",
   "moreinfo": "",
   "quantity": null
 },
 {
   "adm_code": "",
   "municipality": "",
   "sector": "Health",
   "activity": "Rehabilitation of two PRCS hospitals ",
   "organisation": "Danish Red Cross",
   "status": "Ongoing",
   "startdate": "01/10/2015",
   "enddate": "30/09/2016",
   "moreinfo": "",
   "quantity": null
 },
 {
   "adm_code": "",
   "municipality": "",
   "sector": "Organisational Development",
   "activity": "Running of 12 SARC Subbranches",
   "organisation": "Danish Red Cross",
   "status": "Ongoing",
   "startdate": "01/01/2015",
   "enddate": "31/12/2017",
   "moreinfo": "",
   "quantity": null
 },
 {
   "adm_code": "",
   "municipality": "",
   "sector": "Organisational Development",
   "activity": "Running of SARC subbranch in Ariha",
   "organisation": "Danish Red Cross",
   "status": "Ongoing",
   "startdate": "01/04/2015",
   "enddate": "31/12/2016",
   "moreinfo": "",
   "quantity": null
 },
 {
   "adm_code": "",
   "municipality": "",
   "sector": "Health",
   "activity": "Running of SARC Emergency Health Post in Idleb",
   "organisation": "Danish Red Cross",
   "status": "Ongoing",
   "startdate": "01/04/2015",
   "enddate": "31/12/2016",
   "moreinfo": "",
   "quantity": null
 },
 {
   "adm_code": "",
   "municipality": "",
   "sector": "WASH/WATSAN",
   "activity": "Provision of 15.000 Family Hygiene Kits",
   "organisation": "Danish Red Cross",
   "status": "Ongoing",
   "startdate": "01/01/2015",
   "enddate": "31/12/2017",
   "moreinfo": "",
   "quantity": null
 },
 {
   "adm_code": "",
   "municipality": "",
   "sector": "Shelter/Settlement/NFI",
   "activity": "NFIs, cash",
   "organisation": "Finnish Red Cross",
   "status": "Ongoing",
   "startdate": "01/05/2015",
   "enddate": "31/03/2016",
   "moreinfo": "",
   "quantity": null
 },
 {
   "adm_code": "",
   "municipality": "",
   "sector": "WASH/WATSAN",
   "activity": "Baby kits",
   "organisation": "German Red Cross",
   "status": "Ongoing",
   "startdate": "01/07/2015",
   "enddate": "31/12/2016",
   "moreinfo": "",
   "quantity": null
 },
 {
   "adm_code": "",
   "municipality": "",
   "sector": "WASH/WATSAN",
   "activity": "Hygiene kits for special needs",
   "organisation": "German Red Cross",
   "status": "Ongoing",
   "startdate": "01/07/2015",
   "enddate": "31/12/2016",
   "moreinfo": "",
   "quantity": null
 },
 {
   "adm_code": "",
   "municipality": "",
   "sector": "Food Security/Nutrition/Livelihood",
   "activity": "Food parcels",
   "organisation": "German Red Cross",
   "status": "Ongoing",
   "startdate": "01/07/2015",
   "enddate": "31/12/2016",
   "moreinfo": "",
   "quantity": null
 },
 {
   "adm_code": "",
   "municipality": "",
   "sector": "Health",
   "activity": "Baby Milk Formula",
   "organisation": "German Red Cross",
   "status": "Ongoing",
   "startdate": "01/07/2015",
   "enddate": "31/12/2016",
   "moreinfo": "",
   "quantity": null
 },
 {
   "adm_code": "",
   "municipality": "",
   "sector": "Health",
   "activity": "Baby Milk Formula",
   "organisation": "German Red Cross",
   "status": "Completed",
   "startdate": "10/12/2015",
   "enddate": "12/02/2016",
   "moreinfo": "",
   "quantity": null
 },
 {
   "adm_code": "",
   "municipality": "",
   "sector": "Logistics",
   "activity": "Rent warehouses, running costs",
   "organisation": "German Red Cross",
   "status": "Ongoing",
   "startdate": "22/04/2015",
   "enddate": "31/08/2016",
   "moreinfo": "",
   "quantity": null
 },
 {
   "adm_code": "",
   "municipality": "",
   "sector": "Health",
   "activity": "Hygiene kits ",
   "organisation": "German Red Cross",
   "status": "Ongoing",
   "startdate": "22/04/2015",
   "enddate": "31/08/2016",
   "moreinfo": "",
   "quantity": null
 },
 {
   "adm_code": "",
   "municipality": "",
   "sector": "Logistics",
   "activity": "Rent warehouses, running costs",
   "organisation": "German Red Cross",
   "status": "Ongoing",
   "startdate": "01/07/2015",
   "enddate": "31/12/2016",
   "moreinfo": "",
   "quantity": null
 },
 {
   "adm_code": "",
   "municipality": "",
   "sector": "Logistics",
   "activity": "Rehabilitation, construction, warehouse equipment",
   "organisation": "German Red Cross",
   "status": "Ongoing",
   "startdate": "01/07/2015",
   "enddate": "31/12/2016",
   "moreinfo": "",
   "quantity": null
 },
 {
   "adm_code": "",
   "municipality": "",
   "sector": "Logistics",
   "activity": "Logistics staff support",
   "organisation": "German Red Cross",
   "status": "Ongoing",
   "startdate": "01/07/2015",
   "enddate": "31/12/2016",
   "moreinfo": "",
   "quantity": null
 },
 {
   "adm_code": "",
   "municipality": "",
   "sector": "Logistics",
   "activity": "Contribution fuel, maintenance for SARC fleet",
   "organisation": "German Red Cross",
   "status": "Ongoing",
   "startdate": "01/07/2015",
   "enddate": "31/12/2016",
   "moreinfo": "",
   "quantity": null
 },
 {
   "adm_code": "",
   "municipality": "",
   "sector": "Logistics",
   "activity": "Rent warehouses, running costs",
   "organisation": "German Red Cross",
   "status": "Completed",
   "startdate": "01/04/2015",
   "enddate": "30/04/2016",
   "moreinfo": "",
   "quantity": null
 },
 {
   "adm_code": "",
   "municipality": "",
   "sector": "Logistics",
   "activity": "Logistics staff support",
   "organisation": "German Red Cross",
   "status": "Completed",
   "startdate": "01/04/2015",
   "enddate": "30/04/2016",
   "moreinfo": "",
   "quantity": null
 },
 {
   "adm_code": "",
   "municipality": "",
   "sector": "Logistics",
   "activity": "Warehouse rehabilitation ",
   "organisation": "German Red Cross",
   "status": "Completed",
   "startdate": "01/04/2015",
   "enddate": "30/04/2016",
   "moreinfo": "",
   "quantity": null
 },
 {
   "adm_code": "",
   "municipality": "",
   "sector": "Logistics",
   "activity": "Warehouse equipment ",
   "organisation": "German Red Cross",
   "status": "Completed",
   "startdate": "01/04/2015",
   "enddate": "30/04/2016",
   "moreinfo": "",
   "quantity": null
 },
 {
   "adm_code": "",
   "municipality": "",
   "sector": "Logistics",
   "activity": "Fuel and maintenance of vehicles",
   "organisation": "German Red Cross",
   "status": "Completed",
   "startdate": "01/04/2015",
   "enddate": "30/04/2016",
   "moreinfo": "",
   "quantity": null
 },
 {
   "adm_code": "",
   "municipality": "",
   "sector": "WASH/WATSAN",
   "activity": "Baby kits",
   "organisation": "German Red Cross",
   "status": "Completed",
   "startdate": "01/04/2015",
   "enddate": "30/04/2016",
   "moreinfo": "",
   "quantity": null
 },
 {
   "adm_code": "",
   "municipality": "",
   "sector": "Shelter/Settlement/NFI",
   "activity": "400 Tents",
   "organisation": "Syrian Red Crescent",
   "status": "Completed",
   "startdate": "30/01/2016",
   "enddate": "01/03/2016",
   "moreinfo": "",
   "quantity": null
 },
 {
   "adm_code": "",
   "municipality": "",
   "sector": "Health",
   "activity": "Emergency Appeal",
   "organisation": "Japanese Red Cross",
   "status": "Ongoing",
   "startdate": "30/07/2012",
   "enddate": "30/06/2016",
   "moreinfo": "",
   "quantity": null
 },
 {
   "adm_code": "",
   "municipality": "",
   "sector": "Health",
   "activity": "Annual Appeal",
   "organisation": "Japanese Red Cross",
   "status": "Ongoing",
   "startdate": "30/01/2016",
   "enddate": "30/12/2016",
   "moreinfo": "",
   "quantity": null
 },
 {
   "adm_code": "",
   "municipality": "",
   "sector": "Food Security/Nutrition/Livelihood",
   "activity": "home gardenenig",
   "organisation": "Qatar Red Cross",
   "status": "Completed",
   "startdate": "01/06/2015",
   "enddate": "01/06/2016",
   "moreinfo": "",
   "quantity": null
 },
 {
   "adm_code": "",
   "municipality": "",
   "sector": "Food Security/Nutrition/Livelihood",
   "activity": "the project provided farm inputs like seeds, fertilizers, pesticides and fuel for irrigationat for 2,340 ha the rate of $550 per hectare.",
   "organisation": "Qatar Red Cross",
   "status": "Completed",
   "startdate": "01/06/2015",
   "enddate": "01/06/2016",
   "moreinfo": "",
   "quantity": null
 },
 {
   "adm_code": "",
   "municipality": "",
   "sector": "Shelter/Settlement/NFI",
   "activity": "construction of mud houses",
   "organisation": "Qatar Red Cross",
   "status": "Ongoing",
   "startdate": "23/01/2016",
   "enddate": "23/11/2016",
   "moreinfo": "",
   "quantity": null
 },
 {
   "adm_code": "",
   "municipality": "",
   "sector": "Health",
   "activity": "Providing the people with the primary health care services and other specialized health services",
   "organisation": "Qatar Red Cross",
   "status": "Ongoing",
   "startdate": "07/01/2014",
   "enddate": "Ongoing ",
   "moreinfo": "",
   "quantity": null
 },
 {
   "adm_code": "",
   "municipality": "",
   "sector": "Health",
   "activity": "Providing the people with the primary health care services and other specialized health services",
   "organisation": "Qatar Red Cross",
   "status": "Ongoing",
   "startdate": "07/01/2014",
   "enddate": "Ongoing ",
   "moreinfo": "",
   "quantity": null
 },
 {
   "adm_code": "",
   "municipality": "",
   "sector": "Health",
   "activity": "Providing the people with the primary health care services and other specialized health services",
   "organisation": "Qatar Red Cross",
   "status": "Ongoing",
   "startdate": "07/01/2014",
   "enddate": "Ongoing ",
   "moreinfo": "",
   "quantity": null
 },
 {
   "adm_code": "",
   "municipality": "",
   "sector": "Health",
   "activity": "Providing the people with the primary health care services and other specialized health services",
   "organisation": "Qatar Red Cross",
   "status": "Ongoing",
   "startdate": "07/01/2014",
   "enddate": "Ongoing ",
   "moreinfo": "",
   "quantity": null
 },
 {
   "adm_code": "",
   "municipality": "",
   "sector": "Health",
   "activity": "Providing the people with the primary health care services and other specialized health services",
   "organisation": "Qatar Red Cross",
   "status": "Ongoing",
   "startdate": "11/01/2012",
   "enddate": "Ongoing ",
   "moreinfo": "",
   "quantity": null
 },
 {
   "adm_code": "",
   "municipality": "",
   "sector": "Health",
   "activity": "Providing the people with the primary health care services and other specialized health services",
   "organisation": "Qatar Red Cross",
   "status": "Ongoing",
   "startdate": "05/01/2014",
   "enddate": "Ongoing ",
   "moreinfo": "",
   "quantity": null
 },
 {
   "adm_code": "",
   "municipality": "",
   "sector": "Health",
   "activity": "Providing the people with the primary health care services and other specialized health services",
   "organisation": "Qatar Red Cross",
   "status": "Ongoing",
   "startdate": "10/01/2015",
   "enddate": "Ongoing ",
   "moreinfo": "",
   "quantity": null
 },
 {
   "adm_code": "",
   "municipality": "",
   "sector": "Health",
   "activity": "Providing the people with the primary health care services and other specialized health services",
   "organisation": "Qatar Red Cross",
   "status": "Ongoing",
   "startdate": "02/01/2014",
   "enddate": "Ongoing ",
   "moreinfo": "",
   "quantity": null
 },
 {
   "adm_code": "",
   "municipality": "",
   "sector": "Health",
   "activity": "Providing the people with the primary health care services and other specialized health services",
   "organisation": "Qatar Red Cross",
   "status": "Ongoing",
   "startdate": "07/01/2015",
   "enddate": "Ongoing ",
   "moreinfo": "",
   "quantity": null
 },
 {
   "adm_code": "",
   "municipality": "",
   "sector": "Health",
   "activity": "Providing the people with the primary health care services and other specialized health services",
   "organisation": "Qatar Red Cross",
   "status": "Ongoing",
   "startdate": "06/01/2015",
   "enddate": "31/6/2016",
   "moreinfo": "",
   "quantity": null
 },
 {
   "adm_code": "",
   "municipality": "",
   "sector": "Health",
   "activity": "Providing the people with the primary health care services and other specialized health services",
   "organisation": "Qatar Red Cross",
   "status": "Ongoing",
   "startdate": "06/01/2015",
   "enddate": "31/6/2016",
   "moreinfo": "",
   "quantity": null
 },
 {
   "adm_code": "",
   "municipality": "",
   "sector": "Health",
   "activity": "Providing the people with the primary health care services and other specialized health services",
   "organisation": "Qatar Red Cross",
   "status": "Ongoing",
   "startdate": "06/01/2015",
   "enddate": "31/12/2016",
   "moreinfo": "",
   "quantity": null
 },
 {
   "adm_code": "",
   "municipality": "",
   "sector": "Health",
   "activity": "Providing the people with the primary health care services and other specialized health services",
   "organisation": "Qatar Red Cross",
   "status": "Ongoing",
   "startdate": "06/01/2015",
   "enddate": "31/12/2016",
   "moreinfo": "",
   "quantity": null
 },
 {
   "adm_code": "",
   "municipality": "",
   "sector": "Health",
   "activity": "Providing the people with the primary health care services and other specialized health services",
   "organisation": "Qatar Red Cross",
   "status": "Ongoing",
   "startdate": "06/01/2015",
   "enddate": "31/12/2016",
   "moreinfo": "",
   "quantity": null
 },
 {
   "adm_code": "",
   "municipality": "",
   "sector": "Health",
   "activity": "Providing the people with the primary health care services and other specialized health services",
   "organisation": "Qatar Red Cross",
   "status": "Ongoing",
   "startdate": "06/01/2015",
   "enddate": "31/12/2016",
   "moreinfo": "",
   "quantity": null
 },
 {
   "adm_code": "",
   "municipality": "",
   "sector": "Health",
   "activity": "provide IYCF practice counseling for Pregnant and lactating mothers and caregivers, malnutrition screening and active case detecting, referral according to CMAM program, reproductive health program and family planning.",
   "organisation": "Qatar Red Cross",
   "status": "Ongoing",
   "startdate": "09/01/2015",
   "enddate": "30/8/2016",
   "moreinfo": "",
   "quantity": null
 },
 {
   "adm_code": "",
   "municipality": "",
   "sector": "Health",
   "activity": "Giving help to the most vulnerable people who exposed to emergencies due to the contentious bombing and clashes",
   "organisation": "Qatar Red Cross",
   "status": "Ongoing",
   "startdate": "01/01/2015",
   "enddate": "Ongoing ",
   "moreinfo": "",
   "quantity": null
 },
 {
   "adm_code": "",
   "municipality": "",
   "sector": "Health",
   "activity": "independent monitoring of the polio supplementary immunization activities campaigns since October 2013 until now",
   "organisation": "Qatar Red Cross",
   "status": "Ongoing",
   "startdate": "10/01/2013",
   "enddate": "Ongoing ",
   "moreinfo": "",
   "quantity": null
 },
 {
   "adm_code": "",
   "municipality": "",
   "sector": "Food Security/Nutrition/Livelihood",
   "activity": "",
   "organisation": "Qatar Red Cross",
   "status": "Ongoing",
   "startdate": "14/11/2015",
   "enddate": "Ongoing ",
   "moreinfo": "",
   "quantity": null
 },
 {
   "adm_code": "",
   "municipality": "",
   "sector": "Shelter/Settlement/NFI",
   "activity": "",
   "organisation": "Qatar Red Cross",
   "status": "Ongoing",
   "startdate": "06/11/2015",
   "enddate": "Ongoing ",
   "moreinfo": "",
   "quantity": null
 },
 {
   "adm_code": "",
   "municipality": "",
   "sector": "Shelter/Settlement/NFI",
   "activity": "90 High quality Tents",
   "organisation": "Qatar Red Cross",
   "status": "Ongoing",
   "startdate": "08/10/2015",
   "enddate": "Ongoing ",
   "moreinfo": "",
   "quantity": null
 },
 {
   "adm_code": "",
   "municipality": "",
   "sector": "WASH/WATSAN",
   "activity": "",
   "organisation": "Qatar Red Cross",
   "status": "Completed",
   "startdate": "14/2/2016",
   "enddate": "31/03/2016",
   "moreinfo": "",
   "quantity": null
 },
 {
   "adm_code": "",
   "municipality": "",
   "sector": "Food Security/Nutrition/Livelihood",
   "activity": "",
   "organisation": "Qatar Red Cross",
   "status": "Ongoing",
   "startdate": "25/2/2016",
   "enddate": "Ongoing ",
   "moreinfo": "",
   "quantity": null
 },
 {
   "adm_code": "",
   "municipality": "",
   "sector": "Shelter/Settlement/NFI",
   "activity": "",
   "organisation": "Qatar Red Cross",
   "status": "Ongoing",
   "startdate": "03/03/2016",
   "enddate": "Ongoing ",
   "moreinfo": "",
   "quantity": null
 },
 {
   "adm_code": "",
   "municipality": "",
   "sector": "Food Security/Nutrition/Livelihood",
   "activity": "110700 parcels, pledged to Federation Syria appeal",
   "organisation": "Norway Red Cross",
   "status": "Ongoing",
   "startdate": "16/01/2016",
   "enddate": "31/12/2016",
   "moreinfo": "",
   "quantity": null
 },
 {
   "adm_code": "",
   "municipality": "",
   "sector": "Shelter/Settlement/NFI",
   "activity": "168,000 hygiene kits",
   "organisation": "Norway Red Cross",
   "status": "Ongoing",
   "startdate": "01/01/2016",
   "enddate": "31/12/2016",
   "moreinfo": "",
   "quantity": null
 },
 {
   "adm_code": "",
   "municipality": "",
   "sector": "Shelter/Settlement/NFI",
   "activity": "118,000 baby kits",
   "organisation": "Norway Red Cross",
   "status": "Completed",
   "startdate": "01/04/2015",
   "enddate": "01/04/2016",
   "moreinfo": "",
   "quantity": null
 },
 {
   "adm_code": "",
   "municipality": "",
   "sector": "WASH/WATSAN",
   "activity": "- Support SARC preparedness and response projects - e.g. water tanks, small generators, jerry cans and other water in emergency equipment",
   "organisation": "Norway Red Cross",
   "status": "Ongoing",
   "startdate": "01/01/2016",
   "enddate": "31/12/2016",
   "moreinfo": "",
   "quantity": null
 },
 {
   "adm_code": "",
   "municipality": "",
   "sector": "WASH/WATSAN",
   "activity": "- Support SARC water projects to restore water services - e.g. a) replacing malfunctioning pumps, b) restoring electricity by providing generators at pumping stations, c) provide consumables to ensure quality of water",
   "organisation": "Norway Red Cross",
   "status": "Ongoing",
   "startdate": "01/01/2016",
   "enddate": "31/12/2016",
   "moreinfo": "",
   "quantity": null
 },
 {
   "adm_code": "",
   "municipality": "",
   "sector": "WASH/WATSAN",
   "activity": "- Support projects for long-term improvement of living conditions of affected populations and returnees to support their living conditions and recovery",
   "organisation": "Norway Red Cross",
   "status": "Ongoing",
   "startdate": "01/01/2016",
   "enddate": "31/12/2016",
   "moreinfo": "",
   "quantity": null
 }
]